ujson.cpython-35m-darwin.so
ujson_segfault-2.1.57.dist-info/LICENSE.txt
ujson_segfault-2.1.57.dist-info/METADATA
ujson_segfault-2.1.57.dist-info/WHEEL
ujson_segfault-2.1.57.dist-info/top_level.txt
ujson_segfault-2.1.57.dist-info/RECORD
