Metadata-Version: 2.1
Name: ujson-segfault
Version: 2.1.57
Summary: Ultra fast JSON encoder and decoder for Python. Continuing development.
Home-page: https://github.com/segfault/ultrajson
Author: Mark Guzman
Author-email: segfault@hasno.info
License: BSD License
Download-URL: https://github.com/segfault/ultrajson
Platform: any
Classifier: Development Status :: 5 - Production/Stable
Classifier: Intended Audience :: Developers
Classifier: License :: OSI Approved :: BSD License
Classifier: Programming Language :: C
Classifier: Programming Language :: Python :: 3
Classifier: Programming Language :: Python :: 3.4
Classifier: Programming Language :: Python :: 3.5
Classifier: Programming Language :: Python :: 3.6
Classifier: Programming Language :: Python :: 3.7
